{
  "updatedAt": "2026-06-07T12:00:00.000Z",
  "entries": [
    {
      "playerSlug": "travon-hall",
      "playerName": "Tra'Von Hall",
      "pos": "WR",
      "classYear": 2027,
      "school": "Katy, TX · Oklahoma commit",
      "direction": "rising",
      "trigger": "visit_uf_leads",
      "predictionType": "crystal_ball",
      "predictionSchool": "Florida",
      "source": "on3",
      "insider": "On3",
      "headline": "Flip watch: Gainesville visit puts UF in the lead",
      "detail": "Oklahoma commit visited Gainesville May 30–31. On3 recruiting sources list Florida as the top flip candidate with momentum building.",
      "recordedAt": "2026-06-05T20:46:10.390Z"
    },
    {
      "playerSlug": "derrick-malone",
      "playerName": "Derrick Malone",
      "pos": "EDGE",
      "classYear": 2027,
      "school": "Uncommitted",
      "direction": "rising",
      "trigger": "decision_soon_uf",
      "predictionType": "rpm",
      "predictionSchool": "Florida",
      "source": "on3",
      "insider": "On3",
      "headline": "Decision window open — Florida trending after in-home",
      "detail": "On3 RPM and recruiting sources say Florida is trending with a decision close. The in-home visit gave UF clear momentum in the edge race.",
      "decisionDate": "2026-06-15",
      "recordedAt": "2026-06-05T20:46:10.525Z"
    },
    {
      "playerSlug": "devon-hall",
      "playerName": "Devon Hall",
      "pos": "S",
      "classYear": 2027,
      "school": "Ocala, FL",
      "direction": "rising",
      "trigger": "crystal_ball_uf",
      "predictionType": "crystal_ball",
      "predictionSchool": "Florida",
      "source": "on3",
      "insider": "On3",
      "headline": "In-state safety with UF as leading option",
      "detail": "Ocala native with a visit scheduled, strong UF ties, and Florida viewed as the leading option per On3 intel.",
      "recordedAt": "2026-06-05T20:46:10.542Z"
    },
    {
      "playerSlug": "ryan-tillman",
      "playerName": "Ryan Tillman",
      "pos": "WR",
      "classYear": 2027,
      "school": "Katy, TX",
      "direction": "cooling",
      "trigger": "prediction_other",
      "predictionType": "crystal_ball",
      "predictionSchool": "Tennessee",
      "source": "on3",
      "insider": "On3",
      "headline": "Tennessee gaining ground in WR battle",
      "detail": "On3 Crystal Ball momentum has shifted toward Tennessee. Florida needs an urgent campus visit to re-enter the lead pack.",
      "recordedAt": "2026-06-04T18:00:00.000Z"
    },
    {
      "playerSlug": "keondre-jackson",
      "playerName": "Keondre Jackson",
      "pos": "DL",
      "classYear": 2027,
      "school": "Uncommitted",
      "direction": "cooling",
      "trigger": "competitor_offer",
      "predictionType": "insider_intel",
      "predictionSchool": "Georgia",
      "source": "gators_online",
      "insider": "Corey Bender",
      "headline": "Georgia offer complicates Florida's lead",
      "detail": "Gators Online (Corey Bender): a new Georgia offer has complicated Florida's position. UF staff still engaged but momentum has cooled.",
      "recordedAt": "2026-06-03T14:30:00.000Z"
    }
  ],
  "history": {
    "travon-hall": [
      {
        "direction": "rising",
        "trigger": "visit_uf_leads",
        "predictionSchool": "Florida",
        "insider": "On3",
        "recordedAt": "2026-05-28T12:00:00.000Z"
      },
      {
        "direction": "rising",
        "trigger": "visit_uf_leads",
        "predictionSchool": "Florida",
        "insider": "On3",
        "recordedAt": "2026-06-05T20:46:10.390Z"
      }
    ],
    "derrick-malone": [
      {
        "direction": "rising",
        "trigger": "rpm_uf",
        "predictionSchool": "Florida",
        "insider": "On3",
        "recordedAt": "2026-05-20T10:00:00.000Z"
      },
      {
        "direction": "rising",
        "trigger": "decision_soon_uf",
        "predictionSchool": "Florida",
        "insider": "On3",
        "recordedAt": "2026-06-05T20:46:10.525Z"
      }
    ],
    "devon-hall": [
      {
        "direction": "rising",
        "trigger": "crystal_ball_uf",
        "predictionSchool": "Florida",
        "insider": "On3",
        "recordedAt": "2026-06-05T20:46:10.542Z"
      }
    ],
    "ryan-tillman": [
      {
        "direction": "rising",
        "trigger": "crystal_ball_uf",
        "predictionSchool": "Florida",
        "insider": "On3",
        "recordedAt": "2026-05-15T09:00:00.000Z"
      },
      {
        "direction": "cooling",
        "trigger": "prediction_other",
        "predictionSchool": "Tennessee",
        "insider": "On3",
        "recordedAt": "2026-06-04T18:00:00.000Z"
      }
    ],
    "keondre-jackson": [
      {
        "direction": "rising",
        "trigger": "staff_momentum",
        "predictionSchool": "Florida",
        "insider": "Corey Bender",
        "recordedAt": "2026-05-22T11:00:00.000Z"
      },
      {
        "direction": "cooling",
        "trigger": "competitor_offer",
        "predictionSchool": "Georgia",
        "insider": "Corey Bender",
        "recordedAt": "2026-06-03T14:30:00.000Z"
      }
    ]
  }
}
